pyToolkit/__init__.py
pyToolkit/analytics.py
pyToolkit/data_processing.py
pyToolkit/io_tools.py
pyToolkit/plotting.py
pyToolkit/utilities.py
PyToolkit_doxy-0.3.dist-info/METADATA
PyToolkit_doxy-0.3.dist-info/WHEEL
PyToolkit_doxy-0.3.dist-info/top_level.txt
PyToolkit_doxy-0.3.dist-info/RECORD
